hdfscm/__init__.py
hdfscm/_version.py
hdfscm/checkpoints.py
hdfscm/hdfsmanager.py
hdfscm/utils.py
jupyter_hdfscm-0.2.0.dist-info/LICENSE
jupyter_hdfscm-0.2.0.dist-info/METADATA
jupyter_hdfscm-0.2.0.dist-info/WHEEL
jupyter_hdfscm-0.2.0.dist-info/top_level.txt
jupyter_hdfscm-0.2.0.dist-info/RECORD
