Metadata-Version: 2.1
Name: jupyter-hdfscm
Version: 0.2.0
Summary: A Jupyter ContentsManager for HDFS
Home-page: http://github.com/jcrist/hdfscm
Maintainer: Jim Crist
Maintainer-email: jiminy.crist@gmail.com
License: BSD
Project-URL: Source, https://github.com/jcrist/hdfscm
Project-URL: Issue Tracker, https://github.com/jcrist/hdfscm/issues
Keywords: jupyter contentsmanager HDFS Hadoop
Platform: UNKNOWN
Classifier: Topic :: System :: Systems Administration
Classifier: Topic :: System :: Distributed Computing
Classifier: License :: OSI Approved :: BSD License
Classifier: Programming Language :: Python
Classifier: Programming Language :: Python :: 3
Requires-Python: >=3.5
Requires-Dist: notebook (>=4.0)
Requires-Dist: pyarrow (>=0.9.0)
